dbt/adapters/flink/__init__.py
dbt/adapters/flink/__version__.py
dbt/adapters/flink/connections.py
dbt/adapters/flink/impl.py
dbt/include/flink/__init__.py
dbt/include/flink/dbt_project.yml
dbt/include/flink/profile_template.yml
dbt/include/flink/macros/adapters.sql
dbt/include/flink/macros/catalog.sql
dbt_flink-1.2.1.dist-info/LICENSE.md
dbt_flink-1.2.1.dist-info/METADATA
dbt_flink-1.2.1.dist-info/WHEEL
dbt_flink-1.2.1.dist-info/top_level.txt
dbt_flink-1.2.1.dist-info/RECORD
