Metadata-Version: 2.1
Name: dbt-flink
Version: 1.2.1
Summary: The Flink adapter plugin for dbt
Home-page: https://github.com/tritas/dbt-flink
Author: Aris Tritas
Author-email: a.tritas@gmail.com
Classifier: Development Status :: 3 - Alpha
Classifier: License :: OSI Approved :: Apache Software License
Classifier: Operating System :: Microsoft :: Windows
Classifier: Operating System :: MacOS :: MacOS X
Classifier: Operating System :: POSIX :: Linux
Classifier: Programming Language :: Python :: 3.7
Classifier: Programming Language :: Python :: 3.8
Classifier: Programming Language :: Python :: 3.9
Classifier: Programming Language :: Python :: 3.10
Requires-Python: >=3.7
License-File: LICENSE.md
Requires-Dist: dbt-core (~=1.2.0)
